amaterasu/__init__.py
amaterasu/__main__.py
amaterasu/amaterasu.py
amaterasu/utils.py
amaterasu_j2-0.2.2.dist-info/LICENSE
amaterasu_j2-0.2.2.dist-info/METADATA
amaterasu_j2-0.2.2.dist-info/WHEEL
amaterasu_j2-0.2.2.dist-info/entry_points.txt
amaterasu_j2-0.2.2.dist-info/top_level.txt
amaterasu_j2-0.2.2.dist-info/RECORD
