Metadata-Version: 2.1
Name: amaterasu-j2
Version: 0.2.2
Summary: Wandbox API Jinja2 template cli.
Home-page: https://github.com/srz-zumix/amaterasu/
Author: srz_zumix
Author-email: zumix.cpp@gmail.com
License: MIT
Keywords: jinja2,cli,kamidana,Wandbox
Platform: any
Classifier: Development Status :: 4 - Beta
Classifier: Topic :: Utilities
Classifier: License :: OSI Approved :: MIT License
Classifier: Programming Language :: Python
Classifier: Programming Language :: Python :: 3.7
Classifier: Programming Language :: Python :: 3.8
Classifier: Programming Language :: Python :: 3.9
Requires-Dist: requests
Requires-Dist: pyyaml
Requires-Dist: wandbox-api (>=0.9.28)
Requires-Dist: jinja2 (<=3.0.2)
Requires-Dist: markupsafe (==2.0.1)
Requires-Dist: kamidana
Provides-Extra: test
Requires-Dist: importlib-metadata (<2,>=0.12) ; extra == 'test'
Requires-Dist: tox ; extra == 'test'
Requires-Dist: pytest ; extra == 'test'
